wagtail_draftail_snippet/.DS_Store
wagtail_draftail_snippet/__init__.py
wagtail_draftail_snippet/richtext.py
wagtail_draftail_snippet/static/wagtail_draftail_snippet/js/snippet-model-chooser-modal.js
wagtail_draftail_snippet/static/wagtail_draftail_snippet/js/wagtail_draftail_snippet.js
wagtail_draftail_snippet/templates/.DS_Store
wagtail_draftail_snippet/templates/wagtail_draftail_snippet/choose_snippet_model.html
wagtail_draftail_snippet/templates/wagtail_draftail_snippet/results_snippet_model.html
wagtail_draftail_snippet/urls.py
wagtail_draftail_snippet/utils.py
wagtail_draftail_snippet/views.py
wagtail_draftail_snippet/wagtail_hooks.py
wagtail_draftail_snippet-0.2.1.dist-info/LICENSE
wagtail_draftail_snippet-0.2.1.dist-info/WHEEL
wagtail_draftail_snippet-0.2.1.dist-info/METADATA
wagtail_draftail_snippet-0.2.1.dist-info/RECORD
