Metadata-Version: 2.1
Name: wagtail-draftail-snippet
Version: 0.2.1
Summary: Associate RichTextBlock text content to a snippet model.
Home-page: https://github.com/themotleyfool/wagtail-draftail-snippet
License: BSD-3-Clause
Author: Parbhat Puri
Author-email: me@parbhatpuri.com
Requires-Python: >=3.6,<4.0
Classifier: License :: OSI Approved :: BSD License
Classifier: Programming Language :: Python :: 3
Classifier: Programming Language :: Python :: 3.6
Classifier: Programming Language :: Python :: 3.7
Project-URL: Repository, https://github.com/themotleyfool/wagtail-draftail-snippet
